Workbook

Sheet C.Resultado
A1: Cuenta de Pérdidas y Ganancias
A2: 123 - REGION SUR ALIMENTOS SL (B53803557)
A3: Evolución mensual
B4: PERDIDAS Y GANANCIAS | C4: Ape | D4: Ene | E4: Feb | F4: Mar | G4: Abr | H4: May | I4: Jun | J4: Jul | K4: Ago | L4: Sep | M4: Oct | N4: Nov | O4: Dic | P4: Tot
B6: 1. Importe neto de la cifra de negocios | C6: 0 | D6: 236147.59 | E6: 270871.73 | F6: 280949.94 | G6: 442246.51 | H6: 400365.89 | I6: 432347.77 | J6: 525719.39 | K6: 588138.01 | L6: 396636.72 | M6: 391241.81 | N6: 228955.78 | O6: 0 | P6: 4193621.1
B7: 7000 Ventas de mercaderías | C7: 0 | D7: 236147.59 | E7: 270871.73 | F7: 280949.94 | G7: 442246.51 | H7: 400365.89 | I7: 432347.77 | J7: 525719.39 | K7: 588138.01 | L7: 396636.72 | M7: 391241.81 | N7: 228955.78 | O7: 0 | P7: 4193621.1
B8: 4. Aprovisionamientos | C8: 0 | D8: -193420.38 | E8: -212742.59 | F8: -219635.28 | G8: -348220.6 | H8: -300730.39 | I8: -445152.42 | J8: -426699.16 | K8: -429557.48 | L8: -303766.08 | M8: -319107.25 | N8: -139015.77 | O8: 0 | P8: -3338047.4
B9: 6000 Compras de mercaderías | C9: 0 | D9: -193385.42 | E9: -210450.67 | F9: -219169.23 | G9: -348029.61 | H9: -300331.11 | I9: -374511.52 | J9: -425699.08 | K9: -428847.94 | L9: -303198.03 | M9: -318184.84 | N9: -138878.84 | O9: 0 | P9: -3260686.3
B10: 6100 Variación de existencias de mercaderías | C10: 0 | D10: 0 | E10: 0 | F10: 0 | G10: 0 | H10: 0 | I10: -70000 | J10: 0 | K10: 0 | L10: 0 | M10: 0 | N10: 0 | O10: 0 | P10: -70000
B11: 6. Gastos de personal | C11: 0 | D11: -29587.5 | E11: -31847.94 | F11: -33079.9 | G11: -32045.01 | H11: -31441.29 | I11: -31487.54 | J11: -31621.21 | K11: -32001.31 | L11: -33132.09 | M11: -33839.71 | N11: 0 | O11: 0 | P11: -320083.5
B12: 6400 Sueldos y salarios | C12: 0 | D12: -23624.09 | E12: -25565.89 | F12: -25762.53 | G12: -25200.97 | H12: -24489.18 | I12: -24871.92 | J12: -25048.25 | K12: -25159.77 | L12: -25899.92 | M12: -26493.23 | N12: 0 | O12: 0 | P12: -252115.75
B13: 6420 Seguridad Social a cargo de la empresa | C13: 0 | D13: -5963.41 | E13: -6282.05 | F13: -6867.37 | G13: -6844.04 | H13: -6952.11 | I13: -6615.62 | J13: -6382.96 | K13: -6841.54 | L13: -7232.17 | M13: -7346.48 | N13: 0 | O13: 0 | P13: -67327.75
B14: 6490 Otros gastos sociales | C14: 0 | D14: 0 | E14: 0 | F14: -450 | G14: 0 | H14: 0 | I14: 0 | J14: -190 | K14: 0 | L14: 0 | M14: 0 | N14: 0 | O14: 0 | P14: -640
B15: 7. Otros gastos de explotación | C15: 0 | D15: -15243.82 | E15: -19150.98 | F15: -27922.67 | G15: -17873.58 | H15: -19413.88 | I15: -19663.22 | J15: -22293.14 | K15: -14135.82 | L15: -16101.18 | M15: -18410.93 | N15: -6237.27 | O15: -12.26 | P15: -196458.75
B16: 6210 Arrendamientos y cánones | C16: 0 | D16: -3451.51 | E16: -3591.55 | F16: -12150.19 | G16: -3699.45 | H16: -3699.45 | I16: -3745.22 | J16: -5747.88 | K16: -3699.45 | L16: -3699.45 | M16: -1077.1 | N16: -882.59 | O16: 0 | P16: -45443.84
B17: 6220 Reparaciones y conservación | C17: 0 | D17: -2448.78 | E17: -3903.12 | F17: -3846.69 | G17: -1408.02 | H17: -2060.71 | I17: -7472.57 | J17: -2032.64 | K17: -265.11 | L17: -1534.12 | M17: -781.05 | N17: -2495.82 | O17: 0 | P17: -28248.63
... B37: D) RESULTADO DEL EJERCICIO (C+19) | C37: 0 | D37: -6186.05 | E37: 5738.79 | F37: -4125.27 | G37: 40431.6 | H37: 45288.22 | I37: -67667.38 | J37: 41334.95 | K37: 108511.45 | L37: 40137.47 | M37: 15668.55 | N37: 98809.65 | O37: -2520.42 | P37: 315421.56

Sheet C. Resultado 2024
A1: Cuenta de Pérdidas y Ganancias
A2: 123 - REGION SUR ALIMENTOS SL (B53803557)
A3: Evolución mensual
B4: PERDIDAS Y GANANCIAS | C4: Ape | D4: Ene | E4: Feb | F4: Mar | G4: Abr | H4: May | I4: Jun | J4: Jul | K4: Ago | L4: Sep | M4: Oct | N4: Nov | O4: Dic | P4: Tot
B6: 1. Importe neto de la cifra de negocios | C6: 0 | D6: 207249.37 | E6: 240707.93 | F6: 268235.09 | G6: 370853.17 | H6: 350737.96 | I6: 337570.53 | J6: 458502.11 | K6: 513025.97 | L6: 294985.1 | M6: 375675.93 | N6: 233035.7 | O6: 293557.36 | P6: 3944136.2
B7: 7000 Ventas de mercaderías | C7: 0 | D7: 207249.37 | E7: 240707.93 | F7: 268235.09 | G7: 370853.17 | H7: 350737.96 | I7: 337570.53 | J7: 458502.11 | K7: 513025.97 | L7: 294985.1 | M7: 375675.93 | N7: 233035.7 | O7: 293557.36 | P7: 3944136.2
B8: 4. Aprovisionamientos | C8: 0 | D8: -115095.11 | E8: -179494.72 | F8: -252151.52 | G8: -271281.64 | H8: -251635.33 | I8: -268086.57 | J8: -393758.94 | K8: -327500.69 | L8: -247662.09 | M8: -322565.56 | N8: -222541.54 | O8: -363753.19 | P8: -3215526.9
B9: 6000 Compras de mercaderías | C9: 0 | D9: -168504.7 | E9: -218465.36 | F9: -234765.57 | G9: -266066.33 | H9: -262580.39 | I9: -237918.21 | J9: -463623.55 | K9: -346852.22 | L9: -221335.09 | M9: -312936.6 | N9: -206623.78 | O9: -223612.21 | P9: -3163284
B10: 6020 Compras de otros aprovisionamientos | C10: 0 | D10: -1590.41 | E10: -1029.36 | F10: -385.95 | G10: -1215.31 | H10: -54.94 | I10: -168.36 | J10: -135.39 | K10: -648.47 | L10: -327 | M10: -628.96 | N10: -917.76 | O10: -140.98 | P10: -7242.89
B11: 6100 Variación de existencias de mercaderías | C11: 0 | D11: 55000 | E11: 40000 | F11: -17000 | G11: -4000 | H11: 11000 | I11: -30000 | J11: 70000 | K11: 20000 | L11: -26000 | M11: -9000 | N11: -15000 | O11: -140000 | P11: -45000
B12: 6. Gastos de personal | C12: 0 | D12: -20725.13 | E12: -21472.61 | F12: -21719.09 | G12: -23695.43 | H12: -25324.26 | I12: -24818.24 | J12: -24830.93 | K12: -25782.23 | L12: -25983.03 | M12: -27892.75 | N12: -26239.81 | O12: -27086.17 | P12: -295569.68
B13: 6400 Sueldos y salarios | C13: 0 | D13: -16781.39 | E13: -17489.83 | F13: -17264.92 | G13: -18806.5 | H13: -20329.72 | I13: -20179.63 | J13: -20491.93 | K13: -21212.32 | L13: -21459.48 | M13: -21630.94 | N13: -21043.14 | O13: -21661.72 | P13: -238351.52
B14: 6410 Indemnizaciones | C14: 0 | D14: 0 | E14: 0 | F14: 0 | G14: 0 | H14: 0 | I14: 0 | J14: 0 | K14: 0 | L14: 0 | M14: -915.18 | N14: 0 | O14: 0 | P14: -915.18
B15: 6420 Seguridad Social a cargo de la empresa | C15: 0 | D15: -3943.74 | E15: -3982.78 | F15: -4454.17 | G15: -4888.93 | H15: -4994.54 | I15: -4638.61 | J15: -4339 | K15: -4569.91 | L15: -4523.55 | M15: -5346.63 | N15: -5196.67 | O15: -5424.45 | P15: -56302.98
B16: 7. Otros gastos de explotación | C16: 0 | D16: -20037.43 | E16: -13245.75 | F16: -17371.4 | G16: -17775.15 | H16: -17996.37 | I16: -14925.92 | J16: -27395.05 | K16: -17588.89 | L16: -15606.73 | M16: -29568.96 | N16: -15467.15 | O16: -28994.66 | P16: -235973.46
B17: 6210 Arrendamientos y cánones | C17: 0 | D17: -3310.1 | E17: -3310.1 | F17: -3310.1 | G17: -2728.42 | H17: -4013.35 | I17: -3330 | J17: -3330 | K17: -3330 | L17: -3330 | M17: -3330 | N17: -3330 | O17: -3330 | P17: -39982.07
... B40: D) RESULTADO DEL EJERCICIO (C+19) | C40: 0 | D40: 47175.54 | E40: 23650.72 | F40: -26184.1 | G40: 53145.96 | H40: 41629.23 | I40: 25171.24 | J40: 7948 | K40: 137975.99 | L40: 1849.26 | M40: -10064.41 | N40: -35115.7 | O40: -164987.36 | P40: 102194.37

Sheet Explotacion comparativa 
A1: Cuenta de Pérdidas y Ganancias
A2: 123 - REGION SUR ALIMENTOS SL (B53803557)
A3: Evolución mensual
B4: PERDIDAS Y GANANCIAS | C4: 2024 | D4: % | E4: 2025 | F4: % | G4: Ene | H4: % | I4: Feb | J4: % | K4: Mar | L4: % | M4: Abr | N4: % | O4: May | P4: % | Q4: Jun | S4: Jul | U4: Ago | W4: Sep | Y4: Oct | AA4: Nov | AC4: Dic | AD4: Tot
B6: 1. Importe neto de la cifra de negocios | C6: ='C. Resultado 2024'!P6 -> 3,944,136.22 | D6: =C6/C$6*100 -> 100.00 | E6: =G6+I6+K6+M6+O6+Q6+S6+U6+W6+Y6 -> 3,964,665.36 | F6: =E6/$E$6*100 -> 100.00 | G6: =C.Resultado!D6 -> 236,147.59 | H6: =G6/G6*100 -> 100.00 | I6: =C.Resultado!E6 -> 270,871.73 | J6: =I6/$I$6*100 -> 100.00 | K6: =C.Resultado!F6 -> 280,949.94 | L6: =K6/$K$6*100 -> 100.00 | M6: =C.Resultado!G6 -> 442,246.51 | N6: =M6/$M$6*100 -> 100.00 | O6: =C.Resultado!H6 -> 400,365.89 | P6: =O6/$O$6*100 -> 100.00 | Q6: =C.Resultado!I6 -> 432,347.77 | R6: =Q6/Q6*100 -> 100.00 | S6: =C.Resultado!J6 -> 525,719.39 | T6: =S6/$S$6*100 -> 100.00 | U6: =C.Resultado!K6 -> 588,138.01 | V6: =U6/U6*100 -> 100.00 | W6: =C.Resultado!L6 -> 396,636.72 | X6: =W6/$W$6*100 -> 100.00 | Y6: =C.Resultado!M6 -> 391,241.81 | Z6: =Y6/$Y$6*100 -> 100.00 | AA6: =C.Resultado!N6 -> 228,955.78 | AB6: =AA6/$AA$6*100 -> 100.00 | AC6: 0 | AD6: 1630581.7
B7: 7000 Ventas de mercaderías | C7: ='C. Resultado 2024'!P7 -> 3,944,136.22 | D7: =C7/C$6*100 -> 100.00 | E7: =G7+I7+K7+M7+O7+Q7+S7+U7+W7+Y7 -> 3,964,665.36 | F7: =E7/$E$6*100 -> 100.00 | G7: =C.Resultado!D7 -> 236,147.59 | H7: =G7/G7*100 -> 100.00 | I7: =C.Resultado!E7 -> 270,871.73 | J7: =I7/$I$6*100 -> 100.00 | K7: =C.Resultado!F7 -> 280,949.94 | L7: =K7/$K$6*100 -> 100.00 | M7: =C.Resultado!G7 -> 442,246.51 | N7: =M7/$M$6*100 -> 100.00 | O7: =C.Resultado!H7 -> 400,365.89 | P7: =O7/$O$6*100 -> 100.00 | Q7: =C.Resultado!I7 -> 432,347.77 | R7: =Q7/Q7*100 -> 100.00 | S7: =C.Resultado!J7 -> 525,719.39 | T7: =S7/$S$6*100 -> 100.00 | U7: =C.Resultado!K7 -> 588,138.01 | V7: =$U$7/V7 -> #REF! | W7: =C.Resultado!L7 -> 396,636.72 | X7: =W7/$W$6*100 -> 100.00 | Y7: =C.Resultado!M7 -> 391,241.81 | Z7: =Y7/$Y$6*100 -> 100.00 | AA7: =C.Resultado!N7 -> 228,955.78 | AB7: =AA7/$AA$6*100 -> 100.00 | AC7: 0 | AD7: 1630581.7
B8: 4. Aprovisionamientos | C8: ='C. Resultado 2024'!P8 -> -3,215,526.90 | D8: =C8/C$6*100 -> -81.53 | E8: =G8+I8+K8+M8+O8+Q8+S8+U8+W8+Y8 -> -3,199,031.63 | F8: =E8/$E$6*100 -> -80.69 | G8: =C.Resultado!D8 -> -193,420.38 | H8: =G8/$G$6*100 -> -81.91 | I8: =C.Resultado!E8 -> -212,742.59 | J8: =I8/$I$6*100 -> -78.54 | K8: =C.Resultado!F8 -> -219,635.28 | L8: =K8/$K$6*100 -> -78.18 | M8: =C.Resultado!G8 -> -348,220.60 | N8: =M8/$M$6*100 -> -78.74 | O8: =C.Resultado!H8 -> -300,730.39 | P8: =O8/$O$6*100 -> -75.11 | Q8: =C.Resultado!I8 -> -445,152.42 | R8: =Q8/$Q$6*100 -> -102.96 | S8: =C.Resultado!J8 -> -426,699.16 | T8: =S8/$S$6*100 -> -81.16 | U8: =C.Resultado!K8 -> -429,557.48 | V8: =U8/$U$7*100 -> -73.04 | W8: =C.Resultado!L8 -> -303,766.08 | X8: =W8/$W$6*100 -> -76.59 | Y8: =C.Resultado!M8 -> -319,107.25 | Z8: =Y8/$Y$6*100 -> -81.56 | AA8: =C.Resultado!N8 -> -139,015.77 | AB8: =AA8/$AA$6*100 -> -60.72 | AC8: 0 | AD8: -1260725.8
B9: 6000 Compras de mercaderías | C9: ='C. Resultado 2024'!P9 -> -3,163,284.01 | D9: =C9/C$6*100 -> -80.20 | E9: =G9+I9+K9+M9+O9+Q9+S9 -> -2,071,576.64 | F9: =E9/$E$6*100 -> -52.25 | G9: =C.Resultado!D9 -> -193,385.42 | H9: =-G9/$G$6*100 -> 81.89 | I9: =C.Resultado!E9 -> -210,450.67 | J9: =I9/$I$6*100 -> -77.69 | K9: =C.Resultado!F9 -> -219,169.23 | L9: =K9/$K$6*100 -> -78.01 | M9: =C.Resultado!G9 -> -348,029.61 | N9: =M9/$M$6*100 -> -78.70 | O9: =C.Resultado!H9 -> -300,331.11 | P9: =O9/$O$6*100 -> -75.01 | Q9: =C.Resultado!I9 -> -374,511.52 | R9: =Q9/$Q$6*100 -> -86.62 | S9: =C.Resultado!J9 -> -425,699.08 | T9: =S9/$S$6*100 -> -80.97 | U9: =C.Resultado!K9 -> -428,847.94 | V9: =U9/$U$7*100 -> -72.92 | W9: =C.Resultado!L9 -> -303,198.03 | X9: =W9/$W$6*100 -> -76.44 | Y9: =C.Resultado!M9 -> -318,184.84 | Z9: =Y9/$Y$6*100 -> -81.33 | AA9: =C.Resultado!N9 -> -138,878.84 | AB9: =AA9/$AA$6*100 -> -60.66 | AC9: 0 | AD9: -1257342.6
B10: 6020 Compras de otros aprovisionamientos | C10: ='C. Resultado 2024'!P10 -> -7,242.89 | D10: =C10/C$6*100 -> -0.18 | E10: =G10+I10+K10+M10+O10+Q10+S10 -> -70,000.00 | F10: =E10/$E$6*100 -> -1.77 | G10: =C.Resultado!D10 -> 0.00 | H10: =-G10/$G$6*100 -> 0.00 | I10: =C.Resultado!E10 -> 0.00 | J10: =I10/$I$6*100 -> 0.00 | K10: =C.Resultado!F10 -> 0.00 | L10: =K10/$K$6*100 -> 0.00 | M10: =C.Resultado!G10 -> 0.00 | N10: =M10/$M$6*100 -> 0.00 | O10: =C.Resultado!H10 -> 0.00 | P10: =O10/$O$6*100 -> 0.00 | Q10: =C.Resultado!I10 -> -70,000.00 | R10: =Q10/$Q$6*100 -> -16.19 | S10: =C.Resultado!J10 -> 0.00 | T10: =S10/$S$6*100 -> 0.00 | U10: =C.Resultado!K10 -> 0.00 | V10: =U10/$U$7*100 -> 0.00 | W10: =C.Resultado!L10 -> 0.00 | X10: =W10/$W$6*100 -> 0.00 | Y10: =C.Resultado!M10 -> 0.00 | Z10: =Y10/$Y$6*100 -> 0.00 | AA10: =C.Resultado!N10 -> 0.00 | AB10: =AA10/$AA$6*100 -> 0.00 | AC10: 0 | AD10: -3383.2
B11: 6. Gastos de personal | C11: ='C. Resultado 2024'!P12 -> -295,569.68 | D11: =C11/C$6*100 -> -7.49 | E11: =G11+I11+K11+M11+O11+Q11+S11+U11+W11+Y11 -> -320,083.50 | F11: =E11/$E$6*100 -> -8.07 | G11: =C.Resultado!D11 -> -29,587.50 | H11: =-G11/$G$6*100 -> 12.53 | I11: =C.Resultado!E11 -> -31,847.94 | J11: =I11/$I$6*100 -> -11.76 | K11: =C.Resultado!F11 -> -33,079.90 | L11: =K11/$K$6*100 -> -11.77 | M11: =C.Resultado!G11 -> -32,045.01 | N11: =M11/$M$6*100 -> -7.25 | O11: =C.Resultado!H11 -> -31,441.29 | P11: =O11/$O$6*100 -> -7.85 | Q11: =C.Resultado!I11 -> -31,487.54 | R11: =Q11/$Q$6*100 -> -7.28 | S11: =C.Resultado!J11 -> -31,621.21 | T11: =S11/$S$6*100 -> -6.01 | U11: =C.Resultado!K11 -> -32,001.31 | V11: =U11/$U$7*100 -> -5.44 | W11: =C.Resultado!L11 -> -33,132.09 | X11: =W11/$W$6*100 -> -8.35 | Y11: =C.Resultado!M11 -> -33,839.71 | Z11: =Y11/$Y$6*100 -> -8.65 | AA11: =C.Resultado!N11 -> 0.00 | AB11: =AA11/$AA$6*100 -> 0.00 | AC11: 0 | AD11: -158001.64
B12: 6400 Sueldos y salarios | C12: ='C. Resultado 2024'!P12 -> -295,569.68 | D12: =C12/C$6*100 -> -7.49 | E12: =G12+I12+K12+M12+O12+Q12+S12 -> -174,562.83 | F12: =E12/$E$6*100 -> -4.40 | G12: =C.Resultado!D12 -> -23,624.09 | H12: =-G12/$G$6*100 -> 10.00 | I12: =C.Resultado!E12 -> -25,565.89 | J12: =I12/$I$6*100 -> -9.44 | K12: =C.Resultado!F12 -> -25,762.53 | L12: =K12/$K$6*100 -> -9.17 | M12: =C.Resultado!G12 -> -25,200.97 | N12: =M12/$M$6*100 -> -5.70 | O12: =C.Resultado!H12 -> -24,489.18 | P12: =O12/$O$6*100 -> -6.12 | Q12: =C.Resultado!I12 -> -24,871.92 | R12: =Q12/$Q$6*100 -> -5.75 | S12: =C.Resultado!J12 -> -25,048.25 | T12: =S12/$S$6*100 -> -4.76 | U12: =C.Resultado!K12 -> -25,159.77 | V12: =U12/$U$7*100 -> -4.28 | W12: =C.Resultado!L12 -> -25,899.92 | X12: =W12/$W$6*100 -> -6.53 | Y12: =C.Resultado!M12 -> -26,493.23 | Z12: =Y12/$Y$6*100 -> -6.77 | AA12: =C.Resultado!N12 -> 0.00 | AB12: =AA12/$AA$6*100 -> 0.00 | AC12: 0 | AD12: -124642.66
B13: 6420 Seguridad Social a cargo de la empresa | C13: ='C. Resultado 2024'!P13 -> -238,351.52 | D13: =C13/C$6*100 -> -6.04 | E13: =G13+I13+K13+M13+O13+Q13+S13 -> -45,907.56 | F13: =E13/$E$6*100 -> -1.16 | G13: =C.Resultado!D13 -> -5,963.41 | H13: =-G13/$G$6*100 -> 2.53 | I13: =C.Resultado!E13 -> -6,282.05 | J13: =I13/$I$6*100 -> -2.32 | K13: =C.Resultado!F13 -> -6,867.37 | L13: =K13/$K$6*100 -> -2.44 | M13: =C.Resultado!G13 -> -6,844.04 | N13: =M13/$M$6*100 -> -1.55 | O13: =C.Resultado!H13 -> -6,952.11 | P13: =O13/$O$6*100 -> -1.74 | Q13: =C.Resultado!I13 -> -6,615.62 | R13: =Q13/$Q$6*100 -> -1.53 | S13: =C.Resultado!J13 -> -6,382.96 | T13: =S13/$S$6*100 -> -1.21 | U13: =C.Resultado!K13 -> -6,841.54 | V13: =U13/$U$7*100 -> -1.16 | W13: =C.Resultado!L13 -> -7,232.17 | X13: =W13/$W$6*100 -> -1.82 | Y13: =C.Resultado!M13 -> -7,346.48 | Z13: =Y13/$Y$6*100 -> -1.88 | AA13: =C.Resultado!N13 -> 0.00 | AB13: =AA13/$AA$6*100 -> 0.00 | AC13: 0 | AD13: -32908.98
B14: 6490 Otros gastos sociales | C14: ='C. Resultado 2024'!P14 -> -915.18 | D14: =C14/C$6*100 -> -0.02 | E14: =G14+I14+K14+M14+O14+Q14+S14 -> -640.00 | F14: =E14/$E$6*100 -> -0.02 | G14: =C.Resultado!D14 -> 0.00 | H14: =-G14/$G$6*100 -> 0.00 | I14: =C.Resultado!E14 -> 0.00 | J14: =I14/$I$6*100 -> 0.00 | K14: =C.Resultado!F14 -> -450.00 | L14: =K14/$K$6*100 -> -0.16 | M14: =C.Resultado!G14 -> 0.00 | N14: =M14/$M$6*100 -> 0.00 | O14: =C.Resultado!H14 -> 0.00 | P14: =O14/$O$6*100 -> 0.00 | Q14: =C.Resultado!I14 -> 0.00 | R14: =Q14/$Q$6*100 -> 0.00 | S14: =C.Resultado!J14 -> -190.00 | T14: =S14/$S$6*100 -> -0.04 | U14: =C.Resultado!K14 -> 0.00 | V14: =U14/$U$7*100 -> 0.00 | W14: =C.Resultado!L14 -> 0.00 | X14: =W14/$W$6*100 -> 0.00 | Y14: =C.Resultado!M14 -> 0.00 | Z14: =Y14/$Y$6*100 -> 0.00 | AA14: =C.Resultado!N14 -> 0.00 | AB14: =AA14/$AA$6*100 -> 0.00 | AC14: 0 | AD14: -450
B15: 7. Otros gastos de explotación | C15: ='C. Resultado 2024'!P16 -> -235,973.46 | D15: =C15/C$6*100 -> -5.98 | E15: =G15+I15+K15+M15+O15+Q15+S15+U15+W15+Y15 -> -190,209.22 | F15: =E15/$E$6*100 -> -4.80 | G15: =C.Resultado!D15 -> -15,243.82 | H15: =-G15/$G$6*100 -> 6.46 | I15: =C.Resultado!E15 -> -19,150.98 | J15: =I15/$I$6*100 -> -7.07 | K15: =C.Resultado!F15 -> -27,922.67 | L15: =K15/$K$6*100 -> -9.94 | M15: =C.Resultado!G15 -> -17,873.58 | N15: =M15/$M$6*100 -> -4.04 | O15: =C.Resultado!H15 -> -19,413.88 | P15: =O15/$O$6*100 -> -4.85 | Q15: =C.Resultado!I15 -> -19,663.22 | R15: =Q15/$Q$6*100 -> -4.55 | S15: =C.Resultado!J15 -> -22,293.14 | T15: =S15/$S$6*100 -> -4.24 | U15: =C.Resultado!K15 -> -14,135.82 | V15: =U15/$U$7*100 -> -2.40 | W15: =C.Resultado!L15 -> -16,101.18 | X15: =W15/$W$6*100 -> -4.06 | Y15: =C.Resultado!M15 -> -18,410.93 | Z15: =Y15/$Y$6*100 -> -4.71 | AA15: =C.Resultado!N15 -> -6,237.27 | AB15: =AA15/$AA$6*100 -> -2.72 | AC15: 0 | AD15: -107473.37
B16: 6210 Arrendamientos y cánones | C16: ='C. Resultado 2024'!P17 -> -39,982.07 | D16: =C16/C$6*100 -> -1.01 | E16: =G16+I16+K16+M16+O16+Q16+S16 -> -36,085.25 | F16: =E16/$E$6*100 -> -0.91 | G16: =C.Resultado!D16 -> -3,451.51 | H16: =-G16/$G$6*100 -> 1.46 | I16: =C.Resultado!E16 -> -3,591.55 | J16: =I16/$I$6*100 -> -1.33 | K16: =C.Resultado!F16 -> -12,150.19 | L16: =K16/$K$6*100 -> -4.32 | M16: =C.Resultado!G16 -> -3,699.45 | N16: =M16/$M$6*100 -> -0.84 | O16: =C.Resultado!H16 -> -3,699.45 | P16: =O16/$O$6*100 -> -0.92 | Q16: =C.Resultado!I16 -> -3,745.22 | R16: =Q16/$Q$6*100 -> -0.87 | S16: =C.Resultado!J16 -> -5,747.88 | T16: =S16/$S$6*100 -> -1.09 | U16: =C.Resultado!K16 -> -3,699.45 | V16: =U16/$U$7*100 -> -0.63 | W16: =C.Resultado!L16 -> -3,699.45 | X16: =W16/$W$6*100 -> -0.93 | Y16: =C.Resultado!M16 -> -1,077.10 | Z16: =Y16/$Y$6*100 -> -0.28 | AA16: =C.Resultado!N16 -> -882.59 | AB16: =AA16/$AA$6*100 -> -0.39 | AC16: 0 | AD16: -25554.78
B17: 6220 Reparaciones y conservación | C17: ='C. Resultado 2024'!P18 -> -47,384.37 | D17: =C17/C$6*100 -> -1.20 | E17: =G17+I17+K17+M17+O17+Q17+S17 -> -23,172.53 | F17: =E17/$E$6*100 -> -0.58 | G17: =C.Resultado!D17 -> -2,448.78 | H17: =-G17/$G$6*100 -> 1.04 | I17: =C.Resultado!E17 -> -3,903.12 | J17: =I17/$I$6*100 -> -1.44 | K17: =C.Resultado!F17 -> -3,846.69 | L17: =K17/$K$6*100 -> -1.37 | M17: =C.Resultado!G17 -> -1,408.02 | N17: =M17/$M$6*100 -> -0.32 | O17: =C.Resultado!H17 -> -2,060.71 | P17: =O17/$O$6*100 -> -0.51 | Q17: =C.Resultado!I17 -> -7,472.57 | R17: =Q17/$Q$6*100 -> -1.73 | S17: =C.Resultado!J17 -> -2,032.64 | T17: =S17/$S$6*100 -> -0.39 | U17: =C.Resultado!K17 -> -265.11 | V17: =U17/$U$7*100 -> -0.05 | W17: =C.Resultado!L17 -> -1,534.12 | X17: =W17/$W$6*100 -> -0.39 | Y17: =C.Resultado!M17 -> -781.05 | Z17: =Y17/$Y$6*100 -> -0.20 | AA17: =C.Resultado!N17 -> -2,495.82 | AB17: =AA17/$AA$6*100 -> -1.09 | AC17: 0 | AD17: -21341.08
B18: 6230 Servicios de profesionales indepen. | C18: ='C. Resultado 2024'!P19 -> -12,694.46 | D18: =C18/C$6*100 -> -0.32 | E18: =G18+I18+K18+M18+O18+Q18+S18 -> -7,230.00 | F18: =E18/$E$6*100 -> -0.18 | G18: =C.Resultado!D18 -> -1,090.00 | H18: =-G18/$G$6*100 -> 0.46 | I18: =C.Resultado!E18 -> -1,080.00 | J18: =I18/$I$6*100 -> -0.40 | K18: =C.Resultado!F18 -> -980.00 | L18: =K18/$K$6*100 -> -0.35 | M18: =C.Resultado!G18 -> -1,200.00 | N18: =M18/$M$6*100 -> -0.27 | O18: =C.Resultado!H18 -> -1,040.00 | P18: =O18/$O$6*100 -> -0.26 | Q18: =C.Resultado!I18 -> -800.00 | R18: =Q18/$Q$6*100 -> -0.19 | S18: =C.Resultado!J18 -> -1,040.00 | T18: =S18/$S$6*100 -> -0.20 | U18: =C.Resultado!K18 -> -1,040.00 | V18: =U18/$U$7*100 -> -0.18 | W18: =C.Resultado!L18 -> -1,040.00 | X18: =W18/$W$6*100 -> -0.26 | Y18: =C.Resultado!M18 -> 0.00 | Z18: =Y18/$Y$6*100 -> 0.00 | AA18: =C.Resultado!N18 -> 0.00 | AB18: =AA18/$AA$6*100 -> 0.00 | AC18: 0 | AD18: -4430
B19: 6240 Transportes | C19: ='C. Resultado 2024'!P20 -> -17,433.08 | D19: =C19/C$6*100 -> -0.44 | E19: =G19+I19+K19+M19+O19+Q19+S19 -> -7,996.61 | F19: =E19/$E$6*100 -> -0.20 | G19: =C.Resultado!D19 -> -24.58 | H19: =-G19/$G$6*100 -> 0.01 | I19: =C.Resultado!E19 -> -1,540.97 | J19: =I19/$I$6*100 -> -0.57 | K19: =C.Resultado!F19 -> -1,307.56 | L19: =K19/$K$6*100 -> -0.47 | M19: =C.Resultado!G19 -> -1,468.03 | N19: =M19/$M$6*100 -> -0.33 | O19: =C.Resultado!H19 -> -1,324.42 | P19: =O19/$O$6*100 -> -0.33 | Q19: =C.Resultado!I19 -> -1,119.80 | R19: =Q19/$Q$6*100 -> -0.26 | S19: =C.Resultado!J19 -> -1,211.25 | T19: =S19/$S$6*100 -> -0.23 | U19: =C.Resultado!K19 -> -1,323.17 | V19: =U19/$U$7*100 -> -0.22 | W19: =C.Resultado!L19 -> -1,259.87 | X19: =W19/$W$6*100 -> -0.32 | Y19: =C.Resultado!M19 -> -1,794.71 | Z19: =Y19/$Y$6*100 -> -0.46 | AA19: =C.Resultado!N19 -> 0.00 | AB19: =AA19/$AA$6*100 -> 0.00 | AC19: 0 | AD19: -5665.56
B20: 6250 Primas de seguros | C20: ='C. Resultado 2024'!P21 -> -12,409.14 | D20: =C20/C$6*100 -> -0.31 | E20: =G20+I20+K20+M20+O20+Q20+S20 -> -9,667.96 | F20: =E20/$E$6*100 -> -0.24 | G20: =C.Resultado!D20 -> -1,680.65 | H20: =-G20/$G$6*100 -> 0.71 | I20: =C.Resultado!E20 -> -437.34 | J20: =I20/$I$6*100 -> -0.16 | K20: =C.Resultado!F20 -> -1,615.03 | L20: =K20/$K$6*100 -> -0.57 | M20: =C.Resultado!G20 -> -2,688.54 | N20: =M20/$M$6*100 -> -0.61 | O20: =C.Resultado!H20 -> -1,476.10 | P20: =O20/$O$6*100 -> -0.37 | Q20: =C.Resultado!I20 -> -54.02 | R20: =Q20/$Q$6*100 -> -0.01 | S20: =C.Resultado!J20 -> -1,716.28 | T20: =S20/$S$6*100 -> -0.33 | U20: =C.Resultado!K20 -> 1,215.98 | V20: =U20/$U$7*100 -> 0.21 | W20: =C.Resultado!L20 -> -1,370.17 | X20: =W20/$W$6*100 -> -0.35 | Y20: =C.Resultado!M20 -> -3,107.43 | Z20: =Y20/$Y$6*100 -> -0.79 | AA20: =C.Resultado!N20 -> -1,453.04 | AB20: =AA20/$AA$6*100 -> -0.63 | AC20: 0 | AD20: -7897.66
B21: 6260 Servicios bancarios y similares | C21: ='C. Resultado 2024'!P22 -> -7,244.91 | D21: =C21/C$6*100 -> -0.18 | E21: =G21+I21+K21+M21+O21+Q21+S21 -> 4,234.73 | F21: =E21/$E$6*100 -> 0.11 | G21: =C.Resultado!D21 -> -285.86 | H21: =-G21/$G$6*100 -> 0.12 | I21: =C.Resultado!E21 -> -546.32 | J21: =I21/$I$6*100 -> -0.20 | K21: =C.Resultado!F21 -> -679.10 | L21: =K21/$K$6*100 -> -0.24 | M21: =C.Resultado!G21 -> -482.19 | N21: =M21/$M$6*100 -> -0.11 | O21: =C.Resultado!H21 -> -256.07 | P21: =O21/$O$6*100 -> -0.06 | Q21: =C.Resultado!I21 -> 5,189.88 | R21: =Q21/$Q$6*100 -> 1.20 | S21: =C.Resultado!J21 -> 1,294.39 | T21: =S21/$S$6*100 -> 0.25 | U21: =C.Resultado!K21 -> -198.32 | V21: =U21/$U$7*100 -> -0.03 | W21: =C.Resultado!L21 -> -273.38 | X21: =W21/$W$6*100 -> -0.07 | Y21: =C.Resultado!M21 -> -458.87 | Z21: =Y21/$Y$6*100 -> -0.12 | AA21: =C.Resultado!N21 -> -144.15 | AB21: =AA21/$AA$6*100 -> -0.06 | AC21: 0 | AD21: -2317.47
B22: 6270 Publicidad | C22: ='C. Resultado 2024'!P23 -> -6,583.88 | D22: =C22/C$6*100 -> -0.17 | E22: =G22+I22+K22+M22+O22+Q22+S22 -> -4,924.00 | F22: =E22/$E$6*100 -> -0.12 | G22: =C.Resultado!D22 -> -195.00 | H22: =-G22/$G$6*100 -> 0.08 | I22: =C.Resultado!E22 -> -195.00 | J22: =I22/$I$6*100 -> -0.07 | K22: =C.Resultado!F22 -> -195.00 | L22: =K22/$K$6*100 -> -0.07 | M22: =C.Resultado!G22 -> 0.00 | N22: =M22/$M$6*100 -> 0.00 | O22: =C.Resultado!H22 -> -1,139.00 | P22: =O22/$O$6*100 -> -0.28 | Q22: =C.Resultado!I22 -> -2,484.00 | R22: =Q22/$Q$6*100 -> -0.57 | S22: =C.Resultado!J22 -> -716.00 | T22: =S22/$S$6*100 -> -0.14 | U22: =C.Resultado!K22 -> 0.00 | V22: =U22/$U$7*100 -> 0.00 | W22: =C.Resultado!L22 -> -150.00 | X22: =W22/$W$6*100 -> -0.04 | Y22: =C.Resultado!M22 -> 0.00 | Z22: =Y22/$Y$6*100 -> 0.00 | AA22: =C.Resultado!N22 -> -612.00 | AB22: =AA22/$AA$6*100 -> -0.27 | AC22: 0 | AD22: -1724
B23: 6280 Suministros | C23: ='C. Resultado 2024'!P24 -> -59,412.57 | D23: =C23/C$6*100 -> -1.51 | E23: =G23+I23+K23+M23+O23+Q23+S23 -> -36,685.67 | F23: =E23/$E$6*100 -> -0.93 | G23: =C.Resultado!D23 -> -4,023.35 | H23: =-G23/$G$6*100 -> 1.70 | I23: =C.Resultado!E23 -> -5,457.85 | J23: =I23/$I$6*100 -> -2.01 | K23: =C.Resultado!F23 -> -4,794.15 | L23: =K23/$K$6*100 -> -1.71 | M23: =C.Resultado!G23 -> -4,595.15 | N23: =M23/$M$6*100 -> -1.04 | O23: =C.Resultado!H23 -> -4,066.06 | P23: =O23/$O$6*100 -> -1.02 | Q23: =C.Resultado!I23 -> -4,470.97 | R23: =Q23/$Q$6*100 -> -1.03 | S23: =C.Resultado!J23 -> -9,278.14 | T23: =S23/$S$6*100 -> -1.76 | U23: =C.Resultado!K23 -> -7,030.62 | V23: =U23/$U$7*100 -> -1.20 | W23: =C.Resultado!L23 -> -6,087.51 | X23: =W23/$W$6*100 -> -1.53 | Y23: =C.Resultado!M23 -> -5,703.52 | Z23: =Y23/$Y$6*100 -> -1.46 | AA23: =C.Resultado!N23 -> -54.90 | AB23: =AA23/$AA$6*100 -> -0.02 | AC23: 0 | AD23: -24260.77
B24: 6290 Otros servicios | C24: ='C. Resultado 2024'!P25 -> -27,966.34 | D24: =C24/C$6*100 -> -0.71 | E24: =G24+I24+K24+M24+O24+Q24+S24 -> -16,922.79 | F24: =E24/$E$6*100 -> -0.43 | G24: =C.Resultado!D24 -> -1,624.55 | H24: =-G24/$G$6*100 -> 0.69 | I24: =C.Resultado!E24 -> -1,979.77 | J24: =I24/$I$6*100 -> -0.73 | K24: =C.Resultado!F24 -> -2,354.95 | L24: =K24/$K$6*100 -> -0.84 | M24: =C.Resultado!G24 -> -2,332.20 | N24: =M24/$M$6*100 -> -0.53 | O24: =C.Resultado!H24 -> -2,079.46 | P24: =O24/$O$6*100 -> -0.52 | Q24: =C.Resultado!I24 -> -4,706.52 | R24: =Q24/$Q$6*100 -> -1.09 | S24: =C.Resultado!J24 -> -1,845.34 | T24: =S24/$S$6*100 -> -0.35 | U24: =C.Resultado!K24 -> -1,536.47 | V24: =U24/$U$7*100 -> -0.26 | W24: =C.Resultado!L24 -> -686.68 | X24: =W24/$W$6*100 -> -0.17 | Y24: =C.Resultado!M24 -> -2,059.88 | Z24: =Y24/$Y$6*100 -> -0.53 | AA24: =C.Resultado!N24 -> -594.77 | AB24: =AA24/$AA$6*100 -> -0.26 | AC24: 0 | AD24: -11170.84
B25: 6310 Otros tributos | C25: ='C. Resultado 2024'!P26 -> -4,862.64 | D25: =C25/C$6*100 -> -0.12 | E25: =G25+I25+K25+M25+O25+Q25+S25 -> -3,111.21 | F25: =E25/$E$6*100 -> -0.08 | G25: =C.Resultado!D25 -> -419.54 | H25: =-G25/$G$6*100 -> 0.18 | I25: =C.Resultado!E25 -> -419.06 | J25: =I25/$I$6*100 -> -0.15 | K25: =C.Resultado!F25 -> 0.00 | L25: =K25/$K$6*100 -> 0.00 | M25: =C.Resultado!G25 -> 0.00 | N25: =M25/$M$6*100 -> 0.00 | O25: =C.Resultado!H25 -> -2,272.61 | P25: =O25/$O$6*100 -> -0.57 | Q25: =C.Resultado!I25 -> 0.00 | R25: =Q25/$Q$6*100 -> 0.00 | S25: =C.Resultado!J25 -> 0.00 | T25: =S25/$S$6*100 -> 0.00 | U25: =C.Resultado!K25 -> -258.66 | V25: =U25/$U$7*100 -> -0.04 | W25: =C.Resultado!L25 -> 0.00 | X25: =W25/$W$6*100 -> 0.00 | Y25: =C.Resultado!M25 -> -3,428.37 | Z25: =Y25/$Y$6*100 -> -0.88 | AA25: =C.Resultado!N25 -> 0.00 | AB25: =AA25/$AA$6*100 -> 0.00 | AC25: 0 | AD25: -3111.21
B26: 8. Amortización del inmovilizado | C26: ='C. Resultado 2024'!P27 -> -28,625.92 | D26: =C26/C$6*100 -> -0.73 | E26: =G26+I26+K26+M26+O26+Q26+S26+U26+W26+Y26 -> -24,074.25 | F26: =E26/$E$6*100 -> -0.61 | G26: =C.Resultado!D26 -> -2,394.24 | H26: =-G26/$G$6*100 -> 1.01 | I26: =C.Resultado!E26 -> -2,162.56 | J26: =I26/$I$6*100 -> -0.80 | K26: =C.Resultado!F26 -> -2,405.99 | L26: =K26/$K$6*100 -> -0.86 | M26: =C.Resultado!G26 -> -2,332.99 | N26: =M26/$M$6*100 -> -0.53 | O26: =C.Resultado!H26 -> -2,438.22 | P26: =O26/$O$6*100 -> -0.61 | Q26: =C.Resultado!I26 -> -2,388.43 | R26: =Q26/$Q$6*100 -> -0.55 | S26: =C.Resultado!J26 -> -2,508.19 | T26: =S26/$S$6*100 -> -0.48 | U26: =C.Resultado!K26 -> -2,508.16 | V26: =U26/$U$7*100 -> -0.43 | W26: =C.Resultado!L26 -> -2,427.27 | X26: =W26/$W$6*100 -> -0.61 | Y26: =C.Resultado!M26 -> -2,508.20 | Z26: =Y26/$Y$6*100 -> -0.64 | AA26: =C.Resultado!N26 -> -2,427.26 | AB26: =AA26/$AA$6*100 -> -1.06 | AC26: -2394.21 | AD26: -28190.25
B27: 6800 Amortización del inmovilizado intangible | C27: ='C. Resultado 2024'!P28 -> -4,928.94 | D27: =C27/C$6*100 -> -0.12 | E27: =G27+I27+K27+M27+O27+Q27+S27 -> -3,080.91 | F27: =E27/$E$6*100 -> -0.08 | G27: =C.Resultado!D27 -> -450.51 | H27: =-G27/$G$6*100 -> 0.19 | I27: =C.Resultado!E27 -> -406.91 | J27: =I27/$I$6*100 -> -0.15 | K27: =C.Resultado!F27 -> -450.51 | L27: =K27/$K$6*100 -> -0.16 | M27: =C.Resultado!G27 -> -435.98 | N27: =M27/$M$6*100 -> -0.10 | O27: =C.Resultado!H27 -> -450.51 | P27: =O27/$O$6*100 -> -0.11 | Q27: =C.Resultado!I27 -> -435.98 | R27: =Q27/$Q$6*100 -> -0.10 | S27: =C.Resultado!J27 -> -450.51 | T27: =S27/$S$6*100 -> -0.09 | U27: =C.Resultado!K27 -> -450.51 | V27: =U27/$U$7*100 -> -0.08 | W27: =C.Resultado!L27 -> -435.98 | X27: =W27/$W$6*100 -> -0.11 | Y27: =C.Resultado!M27 -> -450.51 | Z27: =Y27/$Y$6*100 -> -0.12 | AA27: =C.Resultado!N27 -> -435.98 | AB27: =AA27/$AA$6*100 -> -0.19 | AC27: -450.51 | AD27: -5304.4
B28: 6810 Amortización del inmovilizado material | C28: ='C. Resultado 2024'!P29 -> -23,696.98 | D28: =C28/C$6*100 -> -0.60 | E28: =G28+I28+K28+M28+O28+Q28+S28 -> -13,549.71 | F28: =E28/$E$6*100 -> -0.34 | G28: =C.Resultado!D28 -> -1,943.73 | H28: =-G28/$G$6*100 -> 0.82 | I28: =C.Resultado!E28 -> -1,755.65 | J28: =I28/$I$6*100 -> -0.65 | K28: =C.Resultado!F28 -> -1,955.48 | L28: =K28/$K$6*100 -> -0.70 | M28: =C.Resultado!G28 -> -1,897.01 | N28: =M28/$M$6*100 -> -0.43 | O28: =C.Resultado!H28 -> -1,987.71 | P28: =O28/$O$6*100 -> -0.50 | Q28: =C.Resultado!I28 -> -1,952.45 | R28: =Q28/$Q$6*100 -> -0.45 | S28: =C.Resultado!J28 -> -2,057.68 | T28: =S28/$S$6*100 -> -0.39 | U28: =C.Resultado!K28 -> -2,057.65 | V28: =U28/$U$7*100 -> -0.35 | W28: =C.Resultado!L28 -> -1,991.29 | X28: =W28/$W$6*100 -> -0.50 | Y28: =C.Resultado!M28 -> -2,057.69 | Z28: =Y28/$Y$6*100 -> -0.53 | AA28: =C.Resultado!N28 -> -1,991.28 | AB28: =AA28/$AA$6*100 -> -0.87 | AC28: -1943.7 | AD28: -22885.85
B29: 12. Otros resultados | C29: ='C. Resultado 2024'!P30 -> -9,792.72 | D29: =C29/C$6*100 -> -0.25 | E29: =G29+I29+K29+M29+O29+Q29+S29 -> 2,610.60 | F29: =E29/$E$6*100 -> 0.07 | G29: =C.Resultado!D29 -> 0.56 | H29: =-G29/$G$6*100 -> 0.00 | I29: =C.Resultado!E29 -> 2,327.00 | J29: =I29/$I$6*100 -> 0.86 | K29: =C.Resultado!F29 -> 249.88 | L29: =K29/$K$6*100 -> 0.09 | M29: =C.Resultado!G29 -> 24.36 | N29: =M29/$M$6*100 -> 0.01 | O29: =C.Resultado!H29 -> 0.00 | P29: =O29/$O$6*100 -> 0.00 | Q29: =C.Resultado!I29 -> 8.80 | R29: =Q29/$Q$6*100 -> 0.00 | S29: =C.Resultado!J29 -> 0.00 | T29: =S29/$S$6*100 -> 0.00 | U29: =C.Resultado!K29 -> 0.00 | V29: =U29/$U$7*100 -> 0.00 | W29: =C.Resultado!L29 -> 0.00 | X29: =W29/$W$6*100 -> 0.00 | Y29: =C.Resultado!M29 -> 0.00 | Z29: =Y29/$Y$6*100 -> 0.00 | AA29: =C.Resultado!N29 -> 14.28 | AB29: =AA29/$AA$6*100 -> 0.01 | AC29: 0 | AD29: 2601.8
B30: 7780 Ingresos excepcionales | C30: ='C. Resultado 2024'!P30 -> -9,792.72 | D30: =C30/C$6*100 -> -0.25 | E30: =G30+I30+K30+M30+O30+Q30+S30 -> 2,610.60 | F30: =E30/$E$6*100 -> 0.07 | G30: =C.Resultado!D30 -> 0.56 | H30: =-G30/$G$6*100 -> 0.00 | I30: =C.Resultado!E30 -> 2,327.00 | J30: =I30/$I$6*100 -> 0.86 | K30: =C.Resultado!F30 -> 249.88 | L30: =K30/$K$6*100 -> 0.09 | M30: =C.Resultado!G30 -> 24.36 | N30: =M30/$M$6*100 -> 0.01 | O30: =C.Resultado!H30 -> 0.00 | P30: =O30/$O$6*100 -> 0.00 | Q30: =C.Resultado!I30 -> 8.80 | R30: =Q30/$Q$6*100 -> 0.00 | S30: =C.Resultado!J30 -> 0.00 | T30: =S30/$S$6*100 -> 0.00 | U30: =C.Resultado!K30 -> 0.00 | V30: =U30/$U$7*100 -> 0.00 | W30: =C.Resultado!L30 -> 0.00 | X30: =W30/$W$6*100 -> 0.00 | Y30: =C.Resultado!M30 -> 0.00 | Z30: =Y30/$Y$6*100 -> 0.00 | AA30: =C.Resultado!N30 -> 14.28 | AB30: =AA30/$AA$6*100 -> 0.01 | AC30: 0 | AD30: 2601.8
B31: A) RESULTADO DE EXPLOTACIÓN | C31: ='C. Resultado 2024'!P33 -> 158,647.54 | D31: =C31/C$6*100 -> 4.02 | E31: =G31+I31+K31+M31+O31+Q31+S31 -> 65,356.30 | F31: =E31/$E$6*100 -> 1.65 | G31: =C.Resultado!D31 -> -4,497.79 | H31: =-G31/$G$6*100 -> 1.90 | I31: =C.Resultado!E31 -> 7,294.66 | J31: =I31/$I$6*100 -> 2.69 | K31: =C.Resultado!F31 -> -1,844.02 | L31: =K31/$K$6*100 -> -0.66 | M31: =C.Resultado!G31 -> 41,798.69 | N31: =M31/$M$6*100 -> 9.45 | O31: =C.Resultado!H31 -> 46,342.11 | P31: =O31/$O$6*100 -> 11.57 | Q31: =C.Resultado!I31 -> -66,335.04 | R31: =Q31/$Q$6*100 -> -15.34 | S31: =C.Resultado!J31 -> 42,597.69 | T31: =S31/$S$6*100 -> 8.10 | U31: =C.Resultado!K31 -> 109,935.24 | V31: =U31/$U$7*100 -> 18.69 | W31: =C.Resultado!L31 -> 41,210.10 | X31: =W31/$W$6*100 -> 10.39 | Y31: =C.Resultado!M31 -> 17,375.72 | Z31: =Y31/$Y$6*100 -> 4.44 | AA31: =C.Resultado!N31 -> 81,289.76 | AB31: =AA31/$AA$6*100 -> 35.50 | AC31: -2394.21 | AD31: 78792.37
B32: 14. Gastos financieros | C32: ='C. Resultado 2024'!P34 -> -21,772.38 | D32: =C32/C$6*100 -> -0.55 | E32: =G32+I32+K32+M32+O32+Q32+S32+U32+W32+Y32 -> -14,745.03 | F32: =E32/$E$6*100 -> -0.37 | G32: =C.Resultado!D32 -> -1,688.26 | H32: =-G32/$G$6*100 -> 0.71 | I32: =C.Resultado!E32 -> -1,555.87 | J32: =I32/$I$6*100 -> -0.57 | K32: =C.Resultado!F32 -> -2,281.25 | L32: =K32/$K$6*100 -> -0.81 | M32: =C.Resultado!G32 -> -1,367.09 | N32: =M32/$M$6*100 -> -0.31 | O32: =C.Resultado!H32 -> -1,053.89 | P32: =O32/$O$6*100 -> -0.26 | Q32: =C.Resultado!I32 -> -1,332.34 | R32: =Q32/$Q$6*100 -> -0.31 | S32: =C.Resultado!J32 -> -1,262.74 | T32: =S32/$S$6*100 -> -0.24 | U32: =C.Resultado!K32 -> -1,423.79 | V32: =U32/$U$7*100 -> -0.24 | W32: =C.Resultado!L32 -> -1,072.63 | X32: =W32/$W$6*100 -> -0.27 | Y32: =C.Resultado!M32 -> -1,707.17 | Z32: =Y32/$Y$6*100 -> -0.44 | AA32: =C.Resultado!N32 -> 17,519.89 | AB32: =AA32/$AA$6*100 -> 7.65 | AC32: 0 | AD32: -7407.09
B33: 6620 Intereses de deudas, empresas grupo | C33: ='C. Resultado 2024'!P34 -> -21,772.38 | D33: =C33/C$6*100 -> -0.55 | E33: =G33+I33+K33+M33+O33+Q33+S33 -> -5,801.21 | F33: =E33/$E$6*100 -> -0.15 | G33: =C.Resultado!D33 -> 0.00 | H33: =-G33/$G$6*100 -> 0.00 | I33: =C.Resultado!E33 -> -66.16 | J33: =I33/$I$6*100 -> -0.02 | K33: =C.Resultado!F33 -> -1,922.39 | L33: =K33/$K$6*100 -> -0.68 | M33: =C.Resultado!G33 -> -1,083.74 | N33: =M33/$M$6*100 -> -0.25 | O33: =C.Resultado!H33 -> -773.99 | P33: =O33/$O$6*100 -> -0.19 | Q33: =C.Resultado!I33 -> -1,045.46 | R33: =Q33/$Q$6*100 -> -0.24 | S33: =C.Resultado!J33 -> -909.47 | T33: =S33/$S$6*100 -> -0.17 | U33: =C.Resultado!K33 -> -1,004.64 | V33: =U33/$U$7*100 -> -0.17 | W33: =C.Resultado!L33 -> -851.96 | X33: =W33/$W$6*100 -> -0.21 | Y33: =C.Resultado!M33 -> -1,220.75 | Z33: =Y33/$Y$6*100 -> -0.31 | AA33: =C.Resultado!N33 -> 17,837.86 | AB33: =AA33/$AA$6*100 -> 7.79 | AC33: 0 | AD33: -3328.01
B34: 6623 Intereses de deudas, entidades credito | D34: =C34/C$6*100 -> 0.00 | E34: =G34+I34+K34+M34+O34+Q34+S34 -> -4,740.23 | F34: =E34/$E$6*100 -> -0.12 | G34: =C.Resultado!D34 -> -1,688.26 | H34: =-G34/$G$6*100 -> 0.71 | I34: =C.Resultado!E34 -> -1,489.71 | J34: =I34/$I$6*100 -> -0.55 | K34: =C.Resultado!F34 -> -358.86 | L34: =K34/$K$6*100 -> -0.13 | M34: =C.Resultado!G34 -> -283.35 | N34: =M34/$M$6*100 -> -0.06 | O34: =C.Resultado!H34 -> -279.90 | P34: =O34/$O$6*100 -> -0.07 | Q34: =C.Resultado!I34 -> -286.88 | R34: =Q34/$Q$6*100 -> -0.07 | S34: =C.Resultado!J34 -> -353.27 | T34: =S34/$S$6*100 -> -0.07 | U34: =C.Resultado!K34 -> -419.15 | V34: =U34/$U$7*100 -> -0.07 | W34: =C.Resultado!L34 -> -220.67 | X34: =W34/$W$6*100 -> -0.06 | Y34: =C.Resultado!M34 -> -486.42 | Z34: =Y34/$Y$6*100 -> -0.12 | AA34: =C.Resultado!N34 -> -317.97 | AB34: =AA34/$AA$6*100 -> -0.14 | AC34: 0 | AD34: -4079.08
B35: B) RESULTADO FINANCIERO (13+14+15+16+17+18) | C35: ='C. Resultado 2024'!P36 -> -21,772.38 | D35: =C35/C$6*100 -> -0.55 | E35: =G35+I35+K35+M35+O35+Q35+S35 -> -10,541.44 | F35: =E35/$E$6*100 -> -0.27 | G35: =C.Resultado!D35 -> -1,688.26 | H35: =-G35/$G$6*100 -> 0.71 | I35: =C.Resultado!E35 -> -1,555.87 | J35: =I35/$I$6*100 -> -0.57 | K35: =C.Resultado!F35 -> -2,281.25 | L35: =K35/$K$6*100 -> -0.81 | M35: =C.Resultado!G35 -> -1,367.09 | N35: =M35/$M$6*100 -> -0.31 | O35: =C.Resultado!H35 -> -1,053.89 | P35: =O35/$O$6*100 -> -0.26 | Q35: =C.Resultado!I35 -> -1,332.34 | R35: =Q35/$Q$6*100 -> -0.31 | S35: =C.Resultado!J35 -> -1,262.74 | T35: =S35/$S$6*100 -> -0.24 | U35: =C.Resultado!K35 -> -1,423.79 | V35: =U35/$U$7*100 -> -0.24 | W35: =C.Resultado!L35 -> -1,072.63 | X35: =W35/$W$6*100 -> -0.27 | Y35: =C.Resultado!M35 -> -1,707.17 | Z35: =Y35/$Y$6*100 -> -0.44 | AA35: =C.Resultado!N35 -> 17,519.89 | AB35: =AA35/$AA$6*100 -> 7.65 | AC35: 0 | AD35: -7407.09
B36: C) RESULTADO ANTES DE IMPUESTOS (A + B) | C36: ='C. Resultado 2024'!P37 -> 136,875.16 | D36: =C36/C$6*100 -> 3.47 | E36: =G36+I36+K36+M36+O36+Q36+S36+W36+Y36+U36 -> 219,132.33 | F36: =E36/$E$6*100 -> 5.53 | G36: =C.Resultado!D36 -> -6,186.05 | H36: =-G36/$G$6*100 -> 2.62 | I36: =C.Resultado!E36 -> 5,738.79 | J36: =I36/$I$6*100 -> 2.12 | K36: =C.Resultado!F36 -> -4,125.27 | L36: =K36/$K$6*100 -> -1.47 | M36: =C.Resultado!G36 -> 40,431.60 | N36: =M36/$M$6*100 -> 9.14 | O36: =C.Resultado!H36 -> 45,288.22 | P36: =O36/$O$6*100 -> 11.31 | Q36: =C.Resultado!I36 -> -67,667.38 | R36: =Q36/$Q$6*100 -> -15.65 | S36: =C.Resultado!J36 -> 41,334.95 | T36: =S36/$S$6*100 -> 7.86 | U36: =C.Resultado!K36 -> 108,511.45 | V36: =U36/$U$7*100 -> 18.45 | W36: =C.Resultado!L36 -> 40,137.47 | X36: =W36/$W$6*100 -> 10.12 | Y36: =C.Resultado!M36 -> 15,668.55 | Z36: =Y36/$Y$6*100 -> 4.00 | AA36: =C.Resultado!N36 -> 98,809.65 | AB36: =AA36/$AA$6*100 -> 43.16 | AD36: 71385.28
B37: D) RESULTADO DEL EJERCICIO (C+19) | C37: ='C. Resultado 2024'!P37 -> 136,875.16 | D37: =C37/C$6*100 -> 3.47 | E37: =G37+I37+K37+M37+O37+Q37+S37+U37+W37+Y37 -> 219,132.33 | F37: =E37/$E$6*100 -> 5.53 | G37: =C.Resultado!D37 -> -6,186.05 | H37: =-G37/$G$6*100 -> 2.62 | I37: =C.Resultado!E37 -> 5,738.79 | J37: =I37/$I$6*100 -> 2.12 | K37: =C.Resultado!F37 -> -4,125.27 | L37: =K37/$K$6*100 -> -1.47 | M37: =C.Resultado!G37 -> 40,431.60 | N37: =M37/$M$6*100 -> 9.14 | O37: =C.Resultado!H37 -> 45,288.22 | P37: =O37/$O$6*100 -> 11.31 | Q37: =C.Resultado!I37 -> -67,667.38 | S37: =C.Resultado!J37 -> 41,334.95 | T37: =S37/$S$6*100 -> 7.86 | U37: =C.Resultado!K37 -> 108,511.45 | V37: =U37/$U$7*100 -> 18.45 | W37: =C.Resultado!L37 -> 40,137.47 | X37: =W37/$W$6*100 -> 10.12 | Y37: =C.Resultado!M37 -> 15,668.55 | Z37: =Y37/$Y$6*100 -> 4.00 | AA37: =C.Resultado!N37 -> 98,809.65 | AB37: =AA37/$AA$6*100 -> 43.16 | AD37: 71385.28

Sheet Graficos 

Sheet Umbral de rentabilidad 
C3: Umbral de rentabilidad
E4: Ene | F4: Feb | G4: Mar | H4: Abr | I4: May | J4: Jun | K4: Jul | L4: Ago | M4: Sep | N4: Oct | O4: Nov | P4: Dic | Q4: Tot
D6: Costes fijos | E6: =C.Resultado!D11+C.Resultado!D15+C.Resultado!D26+C.Resultado!D32 -> -48,913.82 | F6: =C.Resultado!E11+C.Resultado!E15+C.Resultado!E26+C.Resultado!E32 -> -54,717.35 | G6: =C.Resultado!F11+C.Resultado!F15+C.Resultado!F26+C.Resultado!F32 -> -65,689.81 | H6: =C.Resultado!G11+C.Resultado!G15+C.Resultado!G26+C.Resultado!G32 -> -53,618.67 | I6: =C.Resultado!H11+C.Resultado!H15+C.Resultado!H26+C.Resultado!H32 -> -54,347.28 | J6: =C.Resultado!I11+C.Resultado!I15+C.Resultado!I26+C.Resultado!I32 -> -54,871.53 | K6: =C.Resultado!J11+C.Resultado!J15+C.Resultado!J26+C.Resultado!J32 -> -57,685.28 | L6: =C.Resultado!K8+C.Resultado!K11+C.Resultado!K15+C.Resultado!K26+C.Resultado!K32 -> -479,626.56 | M6: =C.Resultado!L8+C.Resultado!L11+C.Resultado!L15+C.Resultado!L26+C.Resultado!L32 -> -356,499.25 | N6: =C.Resultado!M8+C.Resultado!M11+C.Resultado!M15+C.Resultado!M26+C.Resultado!M32 -> -375,573.26 | O6: =C.Resultado!N8+C.Resultado!N11+C.Resultado!N15+C.Resultado!N26+C.Resultado!N32 -> -130,160.41 | P6: =C.Resultado!O8+C.Resultado!O11+C.Resultado!O15+C.Resultado!O26+C.Resultado!O32 -> -2,520.42 | Q6: =C.Resultado!P8+C.Resultado!P11+C.Resultado!P15+C.Resultado!P26+C.Resultado!P32 -> -3,880,824.46
D8: Margen | E8: ='Explotacion comparativa '!F8/100+1 -> 0.19 | F8: ='Explotacion comparativa '!H8/100+1 -> 0.18 | G8: ='Explotacion comparativa '!J8/100+1 -> 0.21 | H8: ='Explotacion comparativa '!N8/100+1 -> 0.21 | I8: 0.2 | J8: 0.19 | K8: 0.19
D11: Ventas | E11: =-E6/E8 -> 253289.4257 | F11: =-F6/F8 -> 302415.4943 | G11: =-G6/G8 -> 306103.1434 | H11: =-H6/H8 -> 252192.9294 | I11: =-I6/I8 -> 271736.4 | J11: =-J6/J8 -> 288797.5263 | K11: =-K6/K8 -> 303606.7368 | L11: =-L6/L8 -> #DIV/0! | ... Q11: =-Q6/Q8 -> #DIV/0!
D13: Total | E13: =SUM(E11:K11) -> 1978141.656
D15: Media | E15: =SUM(E11:K11)/7 -> 282591.6651
D18: Ventas reales | E18: =C.Resultado!D6 -> 236,147.59 | F18: =C.Resultado!E6 -> 270,871.73 | G18: =C.Resultado!F6 -> 280,949.94 | H18: =C.Resultado!G6 -> 442,246.51 | I18: =C.Resultado!H6 -> 400,365.89 | J18: =C.Resultado!I6 -> 432,347.77 | K18: =C.Resultado!J6 -> 525,719.39
D21: Total | E21: =SUM(E18:K18) -> 2,588,648.82
D24: Media | E24: =E21/7 -> 369806.9743
D28: Diferencia | E28: =E24-E15 -> 87215.30915

Sheet Explotacion compartiva año ant
A1: Cuenta de Pérdidas y Ganancias
A2: 123 - REGION SUR ALIMENTOS SL (B53803557)
A3: Evolución mensual
B4: PERDIDAS Y GANANCIAS | C4: Ape | D4: Ene | E4: Feb | F4: Mar | G4: Abr | H4: May | I4: Jun | J4: Jul | K4: Ago | L4: Sep | M4: Oct | N4: Nov | O4: Dic | P4: Tot
B6: 1. Importe neto de la cifra de negocios | C6: 0 | D6: =C.Resultado!D6-'C. Resultado 2024'!D6 -> 28,898.22 | E6: =C.Resultado!E6-'C. Resultado 2024'!E6 -> 30,163.80 | F6: =C.Resultado!F6-'C. Resultado 2024'!F6 -> 12,714.85 | G6: =C.Resultado!G6-'C. Resultado 2024'!G6 -> 71,393.34 | H6: =C.Resultado!H6-'C. Resultado 2024'!H6 -> 49,627.93 | I6: =C.Resultado!I6-'C. Resultado 2024'!I6 -> 94,777.24 | J6: =C.Resultado!J6-'C. Resultado 2024'!J6 -> 67,217.28 | K6: =C.Resultado!K6-'C. Resultado 2024'!K6 -> 75,112.04 | ... O6: =C.Resultado!O6-'C. Resultado 2024'!O6 -> -293,557.36 | P6: 3944136.2
B7: 7000 Ventas de mercaderías | C7: 0 | D7: 207249.37 | E7: 240707.93 | F7: 268235.09 | G7: 370853.17 | H7: 350737.96 | I7: 337570.53 | J7: 458502.11 | K7: 513025.97 | L7: 294985.1 | M7: 375675.93 | N7: 233035.7 | O7: 293557.36 | P7: 3944136.2
B8: 4. Aprovisionamientos | C8: 0 | D8: -115095.11 | E8: -179494.72 | F8: -252151.52 | G8: -271281.64 | H8: -251635.33 | I8: -268086.57 | J8: -393758.94 | K8: -327500.69 | L8: -247662.09 | M8: -322565.56 | N8: -222541.54 | O8: -363753.19 | P8: -3215526.9
B9: 6000 Compras de mercaderías | C9: 0 | D9: -168504.7 | E9: -218465.36 | F9: -234765.57 | G9: -266066.33 | H9: -262580.39 | I9: -237918.21 | J9: -463623.55 | K9: -346852.22 | L9: -221335.09 | M9: -312936.6 | N9: -206623.78 | O9: -223612.21 | P9: -3163284
B10: 6020 Compras de otros aprovisionamientos | C10: 0 | D10: -1590.41 | E10: -1029.36 | F10: -385.95 | G10: -1215.31 | H10: -54.94 | I10: -168.36 | J10: -135.39 | K10: -648.47 | L10: -327 | M10: -628.96 | N10: -917.76 | O10: -140.98 | P10: -7242.89
B11: 6100 Variación de existencias de mercaderías | C11: 0 | D11: 55000 | E11: 40000 | F11: -17000 | G11: -4000 | H11: 11000 | I11: -30000 | J11: 70000 | K11: 20000 | L11: -26000 | M11: -9000 | N11: -15000 | O11: -140000 | P11: -45000
B12: 6. Gastos de personal | C12: 0 | D12: -20725.13 | E12: -21472.61 | F12: -21719.09 | G12: -23695.43 | H12: -25324.26 | I12: -24818.24 | J12: -24830.93 | K12: -25782.23 | L12: -25983.03 | M12: -27892.75 | N12: -26239.81 | O12: -27086.17 | P12: -295569.68
B13: 6400 Sueldos y salarios | C13: 0 | D13: -16781.39 | E13: -17489.83 | F13: -17264.92 | G13: -18806.5 | H13: -20329.72 | I13: -20179.63 | J13: -20491.93 | K13: -21212.32 | L13: -21459.48 | M13: -21630.94 | N13: -21043.14 | O13: -21661.72 | P13: -238351.52
B14: 6410 Indemnizaciones | C14: 0 | D14: 0 | E14: 0 | F14: 0 | G14: 0 | H14: 0 | I14: 0 | J14: 0 | K14: 0 | L14: 0 | M14: -915.18 | N14: 0 | O14: 0 | P14: -915.18
B15: 6420 Seguridad Social a cargo de la empresa | C15: 0 | D15: -3943.74 | E15: -3982.78 | F15: -4454.17 | G15: -4888.93 | H15: -4994.54 | I15: -4638.61 | J15: -4339 | K15: -4569.91 | L15: -4523.55 | M15: -5346.63 | N15: -5196.67 | O15: -5424.45 | P15: -56302.98
B16: 7. Otros gastos de explotación | C16: 0 | D16: -20037.43 | E16: -13245.75 | F16: -17371.4 | G16: -17775.15 | H16: -17996.37 | I16: -14925.92 | J16: -27395.05 | K16: -17588.89 | L16: -15606.73 | M16: -29568.96 | N16: -15467.15 | O16: -28994.66 | P16: -235973.46
B17: 6210 Arrendamientos y cánones | C17: 0 | D17: -3310.1 | E17: -3310.1 | F17: -3310.1 | G17: -2728.42 | H17: -4013.35 | I17: -3330 | J17: -3330 | K17: -3330 | L17: -3330 | M17: -3330 | N17: -3330 | O17: -3330 | P17: -39982.07
B18: 6220 Reparaciones y conservación | C18: 0 | D18: -6135.98 | E18: -1078.57 | F18: -3285.57 | G18: -2012.37 | H18: -1780.22 | I18: -5209.1 | J18: -6790.77 | K18: -871 | L18: -1991.99 | M18: -3530.12 | N18: -2435.98 | O18: -12262.7 | P18: -47384.37
... B40: D) RESULTADO DEL EJERCICIO (C+19) | C40: 0 | D40: 47175.54 | E40: 23650.72 | F40: -26184.1 | G40: 53145.96 | H40: 41629.23 | I40: 25171.24 | J40: 7948 | K40: 137975.99 | L40: 1849.26 | M40: -10064.41 | N40: -35115.7 | O40: -164987.36 | P40: 102194.37
A42: Cuenta de Pérdidas y Ganancias
A43: 123 - REGION SUR ALIMENTOS SL (B53803557)
A44: Evolución mensual
B45: PERDIDAS Y GANANCIAS | C45: Ape | D45: Ene | E45: Feb | F45: Mar | G45: Abr | H45: May | I45: Jun | J45: Jul | K45: Ago | L45: Sep | M45: Oct | N45: Nov | O45: Dic | P45: Tot
B47: 1. Importe neto de la cifra de negocios | C47: 0 | D47: =D6/'C. Resultado 2024'!D6*100 -> 13.94 | E47: =E6/'C. Resultado 2024'!E6*100 -> 12.53 | F47: =F6/'C. Resultado 2024'!F6*100 -> 4.74 | G47: =G6/'C. Resultado 2024'!G6*100 -> 19.25 | H47: =H6/'C. Resultado 2024'!H6*100 -> 14.15 | P47: =(D47+E47+F47+G47+H47+I47+J47+K47+L47+M47+N47+O47)/5 -> 12.92
B48: 7000 Ventas de mercaderías | C48: 0 | D48: 207249.37 | E48: 240707.93 | F48: 268235.09 | G48: 370853.17 | H48: 350737.96 | I48: 337570.53 | J48: 458502.11 | K48: 513025.97 | L48: 294985.1 | M48: 375675.93 | N48: 233035.7 | O48: 293557.36 | P48: 3944136.2
B49: 4. Aprovisionamientos | C49: 0 | D49: -115095.11 | E49: -179494.72 | F49: -252151.52 | G49: -271281.64 | H49: -251635.33 | I49: -268086.57 | J49: -393758.94 | K49: -327500.69 | L49: -247662.09 | M49: -322565.56 | N49: -222541.54 | O49: -363753.19 | P49: -3215526.9
B50: 6000 Compras de mercaderías | C50: 0 | D50: -168504.7 | E50: -218465.36 | F50: -234765.57 | G50: -266066.33 | H50: -262580.39 | I50: -237918.21 | J50: -463623.55 | K50: -346852.22 | L50: -221335.09 | M50: -312936.6 | N50: -206623.78 | O50: -223612.21 | P50: -3163284
B51: 6020 Compras de otros aprovisionamientos | C51: 0 | D51: -1590.41 | E51: -1029.36 | F51: -385.95 | G51: -1215.31 | H51: -54.94 | I51: -168.36 | J51: -135.39 | K51: -648.47 | L51: -327 | M51: -628.96 | N51: -917.76 | O51: -140.98 | P51: -7242.89
B52: 6100 Variación de existencias de mercaderías | C52: 0 | D52: 55000 | E52: 40000 | F52: -17000 | G52: -4000 | H52: 11000 | I52: -30000 | J52: 70000 | K52: 20000 | L52: -26000 | M52: -9000 | N52: -15000 | O52: -140000 | P52: -45000
B53: 6. Gastos de personal | C53: 0 | D53: -20725.13 | E53: -21472.61 | F53: -21719.09 | G53: -23695.43 | H53: -25324.26 | I53: -24818.24 | J53: -24830.93 | K53: -25782.23 | L53: -25983.03 | M53: -27892.75 | N53: -26239.81 | O53: -27086.17 | P53: -295569.68
B54: 6400 Sueldos y salarios | C54: 0 | D54: -16781.39 | E54: -17489.83 | F54: -17264.92 | G54: -18806.5 | H54: -20329.72 | I54: -20179.63 | J54: -20491.93 | K54: -21212.32 | L54: -21459.48 | M54: -21630.94 | N54: -21043.14 | O54: -21661.72 | P54: -238351.52
B55: 6410 Indemnizaciones | C55: 0 | D55: 0 | E55: 0 | F55: 0 | G55: 0 | H55: 0 | I55: 0 | J55: 0 | K55: 0 | L55: 0 | M55: -915.18 | N55: 0 | O55: 0 | P55: -915.18
B56: 6420 Seguridad Social a cargo de la empresa | C56: 0 | D56: -3943.74 | E56: -3982.78 | F56: -4454.17 | G56: -4888.93 | H56: -4994.54 | I56: -4638.61 | J56: -4339 | K56: -4569.91 | L56: -4523.55 | M56: -5346.63 | N56: -5196.67 | O56: -5424.45 | P56: -56302.98
B57: 7. Otros gastos de explotación | C57: 0 | D57: -20037.43 | E57: -13245.75 | F57: -17371.4 | G57: -17775.15 | H57: -17996.37 | I57: -14925.92 | J57: -27395.05 | K57: -17588.89 | L57: -15606.73 | M57: -29568.96 | N57: -15467.15 | O57: -28994.66 | P57: -235973.46
B58: 6210 Arrendamientos y cánones | C58: 0 | D58: -3310.1 | E58: -3310.1 | F58: -3310.1 | G58: -2728.42 | H58: -4013.35 | I58: -3330 | J58: -3330 | K58: -3330 | L58: -3330 | M58: -3330 | N58: -3330 | O58: -3330 | P58: -39982.07
B59: 6220 Reparaciones y conservación | C59: 0 | D59: -6135.98 | E59: -1078.57 | F59: -3285.57 | G59: -2012.37 | H59: -1780.22 | I59: -5209.1 | J59: -6790.77 | K59: -871 | L59: -1991.99 | M59: -3530.12 | N59: -2435.98 | O59: -12262.7 | P59: -47384.37
... B81: D) RESULTADO DEL EJERCICIO (C+19) | C81: 0 | D81: 47175.54 | E81: 23650.72 | F81: -26184.1 | G81: 53145.96 | H81: 41629.23 | I81: 25171.24 | J81: 7948 | K81: 137975.99 | L81: 1849.26 | M81: -10064.41 | N81: -35115.7 | O81: -164987.36 | P81: 102194.37
